tma_flutter/__init__.py
tma_flutter/main.py
tma_flutter/melos/__init__.py
tma_flutter/melos/sources/melos.py
tma_flutter/melos/templates/.gitignore.template
tma_flutter/melos/templates/melos.yaml.template
tma_flutter/melos/templates/pubspec.yaml.template
tma_flutter/modules/layers/__init__.py
tma_flutter/modules/layers/sources/domain.py
tma_flutter/modules/layers/sources/presentation.py
tma_flutter/modules/targets/example/__init__.py
tma_flutter/modules/targets/example/sources/example.py
tma_flutter/modules/targets/example/templates/lib/example.dart
tma_flutter/modules/targets/example/templates/lib/main.dart
tma_flutter/modules/targets/feature/__init__.py
tma_flutter/modules/targets/feature/sources/feature.py
tma_flutter/modules/targets/feature/templates/lib/feature.dart
tma_flutter/modules/targets/interface/__init__.py
tma_flutter/modules/targets/interface/sources/interface.py
tma_flutter/modules/targets/interface/templates/lib/interface.dart
tma_flutter/modules/targets/test/__init__.py
tma_flutter/modules/targets/test/sources/test.py
tma_flutter/modules/targets/test/templates/lib/feature_testing.dart
tma_flutter/modules/targets/test/templates/test/feature_test.dart
tma_flutter/modules/targets/view/__init__.py
tma_flutter/modules/targets/view/sources/view.py
tma_flutter/modules/targets/view/templates/lib/view.dart
tma_flutter/shared/env/__init__.py
tma_flutter/shared/env/sources/description.py
tma_flutter/shared/env/sources/env.py
tma_flutter/shared/env/sources/env.yaml
tma_flutter/shared/env/sources/env_typer.py
tma_flutter/shared/snippets/__init__.py
tma_flutter/shared/snippets/sources/echo.py
tma_flutter/shared/snippets/sources/flutter.py
tma_flutter/shared/snippets/sources/prefix.py
tma_flutter/shared/snippets/sources/shell.py
tma_flutter/shared/snippets/sources/template.py
tma_flutter/shared/snippets/tests/flutter_test.py
tma_flutter-0.1.15.dist-info/METADATA
tma_flutter-0.1.15.dist-info/WHEEL
tma_flutter-0.1.15.dist-info/entry_points.txt
tma_flutter-0.1.15.dist-info/RECORD
