Metadata-Version: 2.1
Name: tma_flutter
Version: 0.1.15
Summary: 
Author: chminii
Author-email: chminipark@gmail.com
Requires-Python: >=3.12,<4.0
Classifier: Programming Language :: Python :: 3
Classifier: Programming Language :: Python :: 3.12
Requires-Dist: jinja2 (>=3.1.4,<4.0.0)
Requires-Dist: pyyaml (>=6.0.2,<7.0.0)
Requires-Dist: typer[all] (>=0.12.4,<0.13.0)
